frigobar/__init__.py
frigobar/__main__.py
frigobar/cli.py
frigobar/frigobar.py
frigobar-10.dist-info/METADATA
frigobar-10.dist-info/WHEEL
frigobar-10.dist-info/entry_points.txt
frigobar-10.dist-info/RECORD
