Metadata-Version: 2.4
Name: frigobar
Version: 10
Summary: Distribute Python scripts to Windows machines without freezing them.
Project-URL: Homepage, https://github.com/ubalklen/Frigobar
Project-URL: Bug Tracker, https://github.com/ubalklen/Frigobar/issues
Author-email: ubalklen <42127323+ubalklen@users.noreply.github.com>
Requires-Dist: pathspec>=0.12.1
